fluxamasynth/__init__.py
fluxamasynth/fluxamasynth.py
fluxamasynth/synth.py
fluxamasynth/testFluxamasynthPi.py
fluxamasynth-1.0.7.dist-info/METADATA
fluxamasynth-1.0.7.dist-info/RECORD
fluxamasynth-1.0.7.dist-info/WHEEL
fluxamasynth-1.0.7.dist-info/top_level.txt
synth/__init__.py
synth/synth.py
