Metadata-Version: 2.1
Name: fluxamasynth
Version: 1.0.7
Summary: A library for the Modern Device Fluxamasynth board.
Home-page: https://github.com/fluxly/fluxamasynthPi
Author: Modern Device
Author-email: shawn@as220.org
License: MIT
Platform: UNKNOWN
Classifier: Programming Language :: Python :: 3
Classifier: License :: OSI Approved :: MIT License
Classifier: Operating System :: OS Independent
Requires-Dist: pyserial
